LICENSE
README.md
compare/__init__.py
compare/cmpr.py
cmpr-0.0.10.dist-info/METADATA
cmpr-0.0.10.dist-info/WHEEL
cmpr-0.0.10.dist-info/licenses/LICENSE
cmpr-0.0.10.dist-info/RECORD
