Metadata-Version: 2.4
Name: cmpr
Version: 0.0.10
Summary: Check data types for deciml_mathematics library.
Project-URL: Homepage, https://github.com/putterPatcher/compare
Project-URL: Issues, https://github.com/putterPatcher/compare/issues
Author-email: Kor Shantanu Nitin <korshantanu@gmail.com>
License: MIT
License-File: LICENSE
Classifier: License :: OSI Approved :: MIT License
Classifier: Operating System :: OS Independent
Classifier: Programming Language :: Python :: 3
Requires-Python: >=3.8
